repustate/__init__.py
repustate-1.2.2.dist-info/DESCRIPTION.rst
repustate-1.2.2.dist-info/METADATA
repustate-1.2.2.dist-info/metadata.json
repustate-1.2.2.dist-info/RECORD
repustate-1.2.2.dist-info/top_level.txt
repustate-1.2.2.dist-info/WHEEL
