Metadata-Version: 2.0
Name: repustate
Version: 1.2.2
Summary: A Python client to the Repustate text analytics API
Home-page: https://www.repustate.com
Author: Repustate Inc.
Author-email: info@repustate.com
License: MIT
Keywords: text analytics sentiment
Platform: UNKNOWN
Classifier: Development Status :: 5 - Production/Stable
Classifier: Intended Audience :: Developers
Classifier: Topic :: Text Processing :: Linguistic
Classifier: License :: OSI Approved :: MIT License
Classifier: Programming Language :: Python :: 2.6
Classifier: Programming Language :: Python :: 2.7
Classifier: Programming Language :: Python :: 3
Classifier: Programming Language :: Python :: 3.2
Classifier: Programming Language :: Python :: 3.3
Classifier: Programming Language :: Python :: 3.4
Requires-Dist: requests
